{
  "tools": [
    {
      "name": "docs",
      "description": "Gets the documentation for an internal package or function. This should be the first place to look for how something works.",
      "inputSchema": {
        "type": "object",
        "properties": {
          "package": {
            "title": "Package Path",
            "type": "string",
            "description": "Package of the function or struct to get documents for."
          },
          "function": {
            "title": "Function Name",
            "type": "string",
            "description": "Function to get information about.  Can be a package level function SomeFunction or a struct SomeStruct, or a struct function SomeStruct.StructFunction. Leave empty to get package level docs."
          }
        },
        "required": ["package"]
      },
      "command": "go doc {{package}} {{function:=\"\"}}"
    },
    {
      "name": "format",
      "description": "Formats the code according to the specified style guide.\n\nThis command runs 'make fmt' to format all code in the project according to the configured style guide.",
      "inputSchema": {
        "type": "object",
        "properties": {
          "package": {
            "title": "Package Path",
            "type": "string",
            "description": "Specific package or file to format (e.g., dir1 | dir2/... | file.go). Leave empty to format all packages."
          }
        },
        "required": []
      },
      "command": "make fmt PKG=\"{{package:=./...}}\""
    },

    {
      "name": "lint",
      "description": "Runs the linter on the code",
      "inputSchema": {
        "type": "object",
        "properties": {
          "package": {
            "title": "Package Path",
            "type": "string",
            "description": "Specific package or file to lint (e.g., dir1 | dir2/... | file.go). Leave empty to lint all packages."
          }
        },
        "required": []
      },
      "command": "make lint PKG=\"{{package:=./...}}\""
    },
   
    {
      "name": "run_tests",
      "description": "Run the test suite for the project.\n\nArgs:\n    package: Optional package path to test (default: all packages)\n\nReturns:\n    Test results and coverage information",
      "inputSchema": {
        "type": "object",
        "properties": {
          "package": {
            "title": "Package Path",
            "type": "string",
            "description": "Specific package to test (e.g., ./cmd/server). Leave empty to test all packages."
          },
          "test": {
            "title": "Test Name",
            "type": "string",
            "description": "Specific test to run (e.g., TestAddition). Leave empty to run all tests."
          }
        },
        "required": ["package"]
      },
      "command": "make test PKG=\"{{package:=./...}}\" RUN=\"{{test:=\"\"}}\""
    },

    {
      "name": "rebuild_unit_test_db",
      "description": "Initializes Or Rebuilds the unit test database.  Use when starting a new project or if there is a schema mismatch in the unit tests.\n\nThis command drops and recreates the unit test database to ensure it matches the current schema.",
      "inputSchema": { "type": "object", "properties": {}, "required": [] },
      "command": "make rebuild-unit-test-db"
    },

    {
      "name": "make_object",
      "description": "Code generates a new internal only model / controller / and migration",
      "inputSchema": {
        "type": "object",
        "properties": {
          "model_name": {
            "title": "Model Name",
            "type": "string",
            "description": "Name of the model to create in snake case."
          },
          "model_plural": {
            "title": "Model Plural",
            "type": "string",
            "description": "Name of the model in plural form using snake case."
          }
        },
        "required": ["model_name", "model_plural"]
      },
      "command": "make code-gen-object model_name=\"{{model_name}}\" model_plural=\"{{model_plural}}\""
    },

    {
      "name": "make_public_object",
      "description": "Code generates a new public facing model / controller / and migration",
      "inputSchema": {
        "type": "object",
        "properties": {
          "model_name": {
            "title": "Model Name",
            "type": "string",
            "description": "Name of the model to create in snake case."
          },
          "model_plural": {
            "title": "Model Plural",
            "type": "string",
            "description": "Name of the model in plural form using snake case."
          }
        },
        "required": ["model_name", "model_plural"]
      },
      "command": "make code-gen-public-object model_name=\"{{model_name}}\" model_plural=\"{{model_plural}}\""
    }
   
  ]
}
